huaweicloudsdkrocketmq/__init__.py
huaweicloudsdkrocketmq/v2/__init__.py
huaweicloudsdkrocketmq/v2/rocketmq_async_client.py
huaweicloudsdkrocketmq/v2/rocketmq_client.py
huaweicloudsdkrocketmq/v2/model/__init__.py
huaweicloudsdkrocketmq/v2/model/alter_auto_volume_expand_config.py
huaweicloudsdkrocketmq/v2/model/batch_create_or_delete_rocketmq_tag_request.py
huaweicloudsdkrocketmq/v2/model/batch_create_or_delete_rocketmq_tag_response.py
huaweicloudsdkrocketmq/v2/model/batch_create_or_delete_tag_req.py
huaweicloudsdkrocketmq/v2/model/batch_delete_consumer_group_req.py
huaweicloudsdkrocketmq/v2/model/batch_delete_consumer_group_resp.py
huaweicloudsdkrocketmq/v2/model/batch_delete_diagnosis_records_for_rocket_mq_request.py
huaweicloudsdkrocketmq/v2/model/batch_delete_diagnosis_records_for_rocket_mq_response.py
huaweicloudsdkrocketmq/v2/model/batch_delete_diagnosis_records_request.py
huaweicloudsdkrocketmq/v2/model/batch_delete_diagnosis_records_response.py
huaweicloudsdkrocketmq/v2/model/batch_delete_diagnosis_report_req.py
huaweicloudsdkrocketmq/v2/model/batch_delete_diagnosis_report_request.py
huaweicloudsdkrocketmq/v2/model/batch_delete_diagnosis_report_response.py
huaweicloudsdkrocketmq/v2/model/batch_delete_instance_req.py
huaweicloudsdkrocketmq/v2/model/batch_delete_instance_resp_results.py
huaweicloudsdkrocketmq/v2/model/batch_delete_instances_request.py
huaweicloudsdkrocketmq/v2/model/batch_delete_instances_response.py
huaweicloudsdkrocketmq/v2/model/batch_delete_rocket_mq_migration_task_request.py
huaweicloudsdkrocketmq/v2/model/batch_delete_rocket_mq_migration_task_response.py
huaweicloudsdkrocketmq/v2/model/batch_delete_topic_req.py
huaweicloudsdkrocketmq/v2/model/batch_delete_topic_resp.py
huaweicloudsdkrocketmq/v2/model/batch_reset_consume_offset_req.py
huaweicloudsdkrocketmq/v2/model/batch_reset_rocket_mq_message_offsets_request.py
huaweicloudsdkrocketmq/v2/model/batch_reset_rocket_mq_message_offsets_response.py
huaweicloudsdkrocketmq-3.1.184.dist-info/METADATA
huaweicloudsdkrocketmq-3.1.184.dist-info/WHEEL
huaweicloudsdkrocketmq-3.1.184.dist-info/licenses/LICENSE
huaweicloudsdkrocketmq-3.1.184.dist-info/RECORD
